daffi_terminals/__about__.py
daffi_terminals/main.py
daffi_terminals/router/__init__.py
daffi_terminals/router/router.py
daffi_terminals/router/static/favicon.ico
daffi_terminals/router/static/index.html
daffi_terminals/router/static/css/fullscreen.min.css
daffi_terminals/router/static/css/main.css
daffi_terminals/router/static/css/xterm.min.css
daffi_terminals/router/static/js/main.js
daffi_terminals/router/static/js/popper.min.js
daffi_terminals/router/static/js/xterm-addon-fit.min.js
daffi_terminals/router/static/js/xterm.min.js
daffi_terminals/worker/__init__.py
daffi_terminals/worker/worker.py
docs/intro.png
docs/sc.png
daffi_terminals-1.0.13.dist-info/METADATA
daffi_terminals-1.0.13.dist-info/WHEEL
daffi_terminals-1.0.13.dist-info/entry_points.txt
daffi_terminals-1.0.13.dist-info/licenses/LICENSE.txt
daffi_terminals-1.0.13.dist-info/RECORD
