Metadata-Version: 2.1
Name: daffi-terminals
Version: 1.0.13
Summary: Remote terminal control
Project-URL: Source, https://github.com/600apples/dafi-terminals
Author-email: Volodymyr Boiko <600apples@gmail.com>
License-Expression: MIT
License-File: LICENSE.txt
Keywords: async,debug,debugging,distributed,embedded,iot,python,remote,remote control,rpc,ssh,stream,webssh
Classifier: Development Status :: 4 - Beta
Classifier: Intended Audience :: Developers
Classifier: Intended Audience :: System Administrators
Classifier: License :: OSI Approved :: MIT License
Classifier: Operating System :: OS Independent
Classifier: Programming Language :: Python :: 3
Classifier: Programming Language :: Python :: 3.8
Classifier: Programming Language :: Python :: 3.9
Classifier: Programming Language :: Python :: 3.10
Classifier: Topic :: Internet
Classifier: Topic :: Software Development :: Libraries :: Python Modules
Classifier: Topic :: Software Development :: Object Brokering
Classifier: Topic :: Software Development :: Testing
Classifier: Topic :: System :: Clustering
Classifier: Topic :: System :: Monitoring
Classifier: Topic :: System :: Networking
Classifier: Topic :: System :: Systems Administration
Requires-Python: >=3.8
Requires-Dist: daffi>=2.2.1
Requires-Dist: fastapi>=0.95.0
Requires-Dist: uvicorn[standard]>=0.21.1
